s1crets/__init__.py
s1crets/cache.py
s1crets/cli.py
s1crets/core.py
s1crets/providers/__init__.py
s1crets/providers/base.py
s1crets/providers/aws/__init__.py
s1crets/providers/aws/base.py
s1crets/providers/aws/ps.py
s1crets/providers/aws/sm.py
s1crets-0.0.12.data/scripts/s1crets
s1crets-0.0.12.dist-info/LICENSE
s1crets-0.0.12.dist-info/METADATA
s1crets-0.0.12.dist-info/WHEEL
s1crets-0.0.12.dist-info/top_level.txt
s1crets-0.0.12.dist-info/RECORD
