Metadata-Version: 2.1
Name: s1crets
Version: 0.0.12
Summary: Convenience wrapper for AWS Parameter Store/Secrets Manager
Home-page: https://github.com/bra-fsn/s1crets
Author: NAGY, Attila
Author-email: nagy.attila@gmail.com
Project-URL: Documentation, https://s1crets.readthedocs.io/en/latest/index.html
Project-URL: Issue tracker, https://github.com/bra-fsn/s1crets/issues
Classifier: Programming Language :: Python
Classifier: License :: OSI Approved :: MIT License
Classifier: Operating System :: OS Independent
License-File: LICENSE
Requires-Dist: cachetools
Requires-Dist: click >=7.0
Requires-Dist: boto3 >=1.9.23
Requires-Dist: requests
Requires-Dist: cloudpickle
